Aletheia.py
AletheiaPy-0.0.5.dist-info/LICENSE.txt
AletheiaPy-0.0.5.dist-info/METADATA
AletheiaPy-0.0.5.dist-info/WHEEL
AletheiaPy-0.0.5.dist-info/top_level.txt
AletheiaPy-0.0.5.dist-info/RECORD
