Metadata-Version: 2.1
Name: AletheiaPy
Version: 0.0.5
Summary: AletheiaPy is a Python wrapper of Aletheia API, which provides access to financial data.
Home-page: https://github.com/lliang17/AletheiaPy
Author: Lyndon Liang
Author-email: lyndon.y.liang@gmail.com
Classifier: Programming Language :: Python :: 3.7
Classifier: License :: OSI Approved :: MIT License
Classifier: Operating System :: OS Independent
License-File: LICENSE.txt
Requires-Dist: requests
